{
  "id": "MDRW2100022831",
  "metadata": {
    "title": "국립국어원 온라인 대화 말뭉치 MDRW2100022831",
    "creator": "국립국어원",
    "distributor": "국립국어원",
    "year": "2021",
    "category": "온라인 대화 > 2인 대화",
    "annotation_level": "원시",
    "sampling": "실시간 대화"
  },
  "document": [
    {
      "id": "MDRW2100022831.1",
      "metadata": {
        "title": "온라인 대화",
        "author": "개인 대화 참여자",
        "publisher": "심심이",
        "date": "20210829",
        "topic": "미용과 건강",
        "speaker": [
          {
            "id": "1",
            "age": "30대",
            "occupation": "기타",
            "sex": "여성",
            "birthplace": "경남",
            "pricipal_residence": "경남",
            "current_residence": "경남",
            "device": "스마트폰",
            "keyboard": "2벌식(쿼티)"
          },
          {
            "id": "2",
            "age": "30대",
            "occupation": "가정 주부",
            "sex": "여성",
            "birthplace": "광주",
            "pricipal_residence": "광주",
            "current_residence": "경남",
            "device": "스마트폰",
            "keyboard": "기타"
          }
        ],
        "setting": {
          "relation": "낯선 사람",
          "intimacy": 0,
          "contact_frequency": "처음 연락한다"
        }
      },
      "utterance": [
        {
          "id": "MDRW2100022831.1.1",
          "form": "name1님 운동하시나요 ㅎㅎ",
          "original_form": "&name1&님 운동하시나요 ㅎㅎ",
          "speaker_id": "2",
          "time": "20210829 22:39"
        },
        {
          "id": "MDRW2100022831.1.2",
          "form": "아뇨 예전엔 수영했는데 요즘은 못해요",
          "original_form": "아뇨 예전엔 수영했는데 요즘은 못해요",
          "speaker_id": "1",
          "time": "20210829 22:44"
        },
        {
          "id": "MDRW2100022831.1.3",
          "form": "우와 수영멋있네요^^",
          "original_form": "우와 수영멋있네요^^",
          "speaker_id": "2",
          "time": "20210829 22:49"
        },
        {
          "id": "MDRW2100022831.1.4",
          "form": "전 운동을 제대로 해본적이 없네요 ㅜ",
          "original_form": "전 운동을 제대로 해본적이 없네요 ㅜ",
          "speaker_id": "2",
          "time": "20210829 22:49"
        },
        {
          "id": "MDRW2100022831.1.5",
          "form": "코시국이라 홈트 해보겠다고 유튭봤는데",
          "original_form": "코시국이라 홈트 해보겠다고 유튭봤는데",
          "speaker_id": "2",
          "time": "20210829 22:50"
        },
        {
          "id": "MDRW2100022831.1.6",
          "form": "생각보다 엄청 힘들더라구요~",
          "original_form": "생각보다 엄청 힘들더라구요~",
          "speaker_id": "2",
          "time": "20210829 22:50"
        },
        {
          "id": "MDRW2100022831.1.7",
          "form": "아아 동작이 잘 안되셨나요?",
          "original_form": "아아 동작이 잘 안되셨나요?",
          "speaker_id": "1",
          "time": "20210829 22:54"
        },
        {
          "id": "MDRW2100022831.1.8",
          "form": "아니요 동작문제는 아니고 체력문제요 ㅋㅋㅋ",
          "original_form": "아니요 동작문제는 아니고 체력문제요 ㅋㅋㅋ",
          "speaker_id": "2",
          "time": "20210829 22:54"
        },
        {
          "id": "MDRW2100022831.1.9",
          "form": "땀이 엄청흐르고 ...ㅋㅋ  쉽게볼게 아니더라구요",
          "original_form": "땀이 엄청흐르고 ...ㅋㅋ  쉽게볼게 아니더라구요",
          "speaker_id": "2",
          "time": "20210829 22:55"
        },
        {
          "id": "MDRW2100022831.1.10",
          "form": "아아 그러셨군요",
          "original_form": "아아 그러셨군요",
          "speaker_id": "1",
          "time": "20210829 23:02"
        },
        {
          "id": "MDRW2100022831.1.11",
          "form": "코로나가 끝나야 밖에나가서 운동할텐데 쉽지않아보이네요 그쵸?ㅜ",
          "original_form": "코로나가 끝나야 밖에나가서 운동할텐데 쉽지않아보이네요 그쵸?ㅜ",
          "speaker_id": "2",
          "time": "20210829 23:22"
        },
        {
          "id": "MDRW2100022831.1.12",
          "form": "제가사는 지역은 한동안  운동시설에서도 계속 확진자가 나왔었거든요",
          "original_form": "제가사는 지역은 한동안  운동시설에서도 계속 확진자가 나왔었거든요",
          "speaker_id": "2",
          "time": "20210829 23:23"
        },
        {
          "id": "MDRW2100022831.1.13",
          "form": "헐 그러셨군요",
          "original_form": "헐 그러셨군요",
          "speaker_id": "1",
          "time": "20210830 00:18"
        },
        {
          "id": "MDRW2100022831.1.14",
          "form": "그러면 정말 가면 안되겠어요",
          "original_form": "그러면 정말 가면 안되겠어요",
          "speaker_id": "1",
          "time": "20210830 00:18"
        },
        {
          "id": "MDRW2100022831.1.15",
          "form": "네 안전안내문자가 계속오니 무섭더라구요~",
          "original_form": "네 안전안내문자가 계속오니 무섭더라구요~",
          "speaker_id": "2",
          "time": "20210830 00:18"
        },
        {
          "id": "MDRW2100022831.1.16",
          "form": "그래서 걷기라도 하려고 많이나갔는데",
          "original_form": "그래서 걷기라도 하려고 많이나갔는데",
          "speaker_id": "2",
          "time": "20210830 00:19"
        },
        {
          "id": "MDRW2100022831.1.17",
          "form": "와..날은덥죠.. 마스크는 쓰고있죠",
          "original_form": "와..날은덥죠.. 마스크는 쓰고있죠",
          "speaker_id": "2",
          "time": "20210830 00:19"
        },
        {
          "id": "MDRW2100022831.1.18",
          "form": "ㅜㅜ",
          "original_form": "ㅜㅜ",
          "speaker_id": "2",
          "time": "20210830 00:19"
        },
        {
          "id": "MDRW2100022831.1.19",
          "form": "여름엔 마스크 쓰고는 제대로 된 활동이 안되더라구요",
          "original_form": "여름엔 마스크 쓰고는 제대로 된 활동이 안되더라구요",
          "speaker_id": "1",
          "time": "20210830 00:21"
        },
        {
          "id": "MDRW2100022831.1.20",
          "form": "어디 아무도 없을 때 나가서 벗고 걷는거면 모를까.. 근데 요즘엔 이것도 눈치보여요",
          "original_form": "어디 아무도 없을 때 나가서 벗고 걷는거면 모를까.. 근데 요즘엔 이것도 눈치보여요",
          "speaker_id": "1",
          "time": "20210830 00:21"
        },
        {
          "id": "MDRW2100022831.1.21",
          "form": "그쵸 .. 확진자가 너무많아서ㅜ",
          "original_form": "그쵸 .. 확진자가 너무많아서ㅜ",
          "speaker_id": "2",
          "time": "20210830 00:25"
        },
        {
          "id": "MDRW2100022831.1.22",
          "form": "그래도 여름가고 선선해지면",
          "original_form": "그래도 여름가고 선선해지면",
          "speaker_id": "2",
          "time": "20210830 00:26"
        },
        {
          "id": "MDRW2100022831.1.23",
          "form": "다시 걷기시작하려구요^^",
          "original_form": "다시 걷기시작하려구요^^",
          "speaker_id": "2",
          "time": "20210830 00:26"
        },
        {
          "id": "MDRW2100022831.1.24",
          "form": "사람이 집에만 있으면",
          "original_form": "사람이 집에만 있으면",
          "speaker_id": "2",
          "time": "20210830 00:26"
        },
        {
          "id": "MDRW2100022831.1.25",
          "form": "몸건강도 몸건강이지만",
          "original_form": "몸건강도 몸건강이지만",
          "speaker_id": "2",
          "time": "20210830 00:26"
        },
        {
          "id": "MDRW2100022831.1.26",
          "form": "정신건강에 해로워요ㅋㅋㅋ",
          "original_form": "정신건강에 해로워요ㅋㅋㅋ",
          "speaker_id": "2",
          "time": "20210830 00:26"
        },
        {
          "id": "MDRW2100022831.1.27",
          "form": "그럼요 우울하다가",
          "original_form": "그럼요 우울하다가",
          "speaker_id": "1",
          "time": "20210830 00:37"
        },
        {
          "id": "MDRW2100022831.1.28",
          "form": "움직이면 괜찮아지더라구요",
          "original_form": "움직이면 괜찮아지더라구요",
          "speaker_id": "1",
          "time": "20210830 00:37"
        }
      ]
    }
  ]
}
