{
  "id": "MDRW2100044989",
  "metadata": {
    "title": "국립국어원 온라인 대화 말뭉치 MDRW2100044989",
    "creator": "국립국어원",
    "distributor": "국립국어원",
    "year": "2021",
    "category": "온라인 대화 > 2인 대화",
    "annotation_level": "원시",
    "sampling": "실시간 대화"
  },
  "document": [
    {
      "id": "MDRW2100044989.1",
      "metadata": {
        "title": "온라인 대화",
        "author": "개인 대화 참여자",
        "publisher": "심심이",
        "date": "20210908",
        "topic": "콘텐츠>영상/음원 콘텐츠",
        "speaker": [
          {
            "id": "1",
            "age": "20대",
            "occupation": "무직/취업 준비생",
            "sex": "여성",
            "birthplace": "서울",
            "pricipal_residence": "서울",
            "current_residence": "서울",
            "device": "스마트폰",
            "keyboard": "2벌식(쿼티)"
          },
          {
            "id": "2",
            "age": "20대",
            "occupation": "학생",
            "sex": "여성",
            "birthplace": "광주",
            "pricipal_residence": "서울",
            "current_residence": "서울",
            "device": "스마트폰",
            "keyboard": "천지인"
          }
        ],
        "setting": {
          "relation": "학교/학원>동기/동창/동급생",
          "intimacy": 4,
          "contact_frequency": "주 1회 미만"
        }
      },
      "utterance": [
        {
          "id": "MDRW2100044989.1.1",
          "form": "정말로...아니 뭐 이유를 대자면 사람들의 눈이 없는 곳에서 살겠다는건데....",
          "original_form": "정말로...아니 뭐 이유를 대자면 사람들의 눈이 없는 곳에서 살겠다는건데....",
          "speaker_id": "2",
          "time": "20210908 00:27"
        },
        {
          "id": "MDRW2100044989.1.2",
          "form": "그냥 젊은 애 둘있는 한부모 가정 어머니의",
          "original_form": "그냥 젊은 애 둘있는 한부모 가정 어머니의",
          "speaker_id": "1",
          "time": "20210908 00:27"
        },
        {
          "id": "MDRW2100044989.1.3",
          "form": "그것 하나로 애들을 시골로 보내기에는.... 시골 삶도 만만치 않은데요",
          "original_form": "그것 하나로 애들을 시골로 보내기에는.... 시골 삶도 만만치 않은데요",
          "speaker_id": "2",
          "time": "20210908 00:28"
        },
        {
          "id": "MDRW2100044989.1.4",
          "form": "응ㅇ응응",
          "original_form": "응ㅇ응응",
          "speaker_id": "2",
          "time": "20210908 00:28"
        },
        {
          "id": "MDRW2100044989.1.5",
          "form": "귀농 일기 어쩌구가 보고 싶엇던거냐고",
          "original_form": "귀농 일기 어쩌구가 보고 싶엇던거냐고",
          "speaker_id": "1",
          "time": "20210908 00:28"
        },
        {
          "id": "MDRW2100044989.1.6",
          "form": "솔직히 옆집 할아버지",
          "original_form": "솔직히 옆집 할아버지",
          "speaker_id": "1",
          "time": "20210908 00:28"
        },
        {
          "id": "MDRW2100044989.1.7",
          "form": "응...그랬던것 같은데 나는 갠적으로 늑대아이 포스터가 감독의 지향점을 가.장 잘보여주고 있다고 생각",
          "original_form": "응...그랬던것 같은데 나는 갠적으로 늑대아이 포스터가 감독의 지향점을 가.장 잘보여주고 있다고 생각",
          "speaker_id": "2",
          "time": "20210908 00:28"
        },
        {
          "id": "MDRW2100044989.1.8",
          "form": "맨날 기웃기웃하는데",
          "original_form": "맨날 기웃기웃하는데",
          "speaker_id": "1",
          "time": "20210908 00:28"
        },
        {
          "id": "MDRW2100044989.1.9",
          "form": "그게더 힘들듯ㅋ",
          "original_form": "그게더 힘들듯ㅋ",
          "speaker_id": "1",
          "time": "20210908 00:28"
        },
        {
          "id": "MDRW2100044989.1.10",
          "form": "내말이 ㅋ 갈려면 아예 산간오지로 가던지...",
          "original_form": "내말이 ㅋ 갈려면 아예 산간오지로 가던지...",
          "speaker_id": "2",
          "time": "20210908 00:29"
        },
        {
          "id": "MDRW2100044989.1.11",
          "form": "그냥 시골 마을로 갔을뿢",
          "original_form": "그냥 시골 마을로 갔을뿢",
          "speaker_id": "1",
          "time": "20210908 00:29"
        },
        {
          "id": "MDRW2100044989.1.12",
          "form": "다른 주민과 거리 매우 가까움",
          "original_form": "다른 주민과 거리 매우 가까움",
          "speaker_id": "1",
          "time": "20210908 00:29"
        },
        {
          "id": "MDRW2100044989.1.13",
          "form": "뭐...애들 반은 늑대니까... 자연주의 삶이 이 아이들에게 더 행복할거라는 그런 생각이었을까 너무 단순....",
          "original_form": "뭐...애들 반은 늑대니까... 자연주의 삶이 이 아이들에게 더 행복할거라는 그런 생각이었을까 너무 단순....",
          "speaker_id": "2",
          "time": "20210908 00:29"
        },
        {
          "id": "MDRW2100044989.1.14",
          "form": "ㅋㅋ진짜로..그리고 학교도 잘보냄 대체뭘가...",
          "original_form": "ㅋㅋ진짜로..그리고 학교도 잘보냄 대체뭘가...",
          "speaker_id": "2",
          "time": "20210908 00:29"
        },
        {
          "id": "MDRW2100044989.1.15",
          "form": "그리고 진짜...대학을 그만두지 말지",
          "original_form": "그리고 진짜...대학을 그만두지 말지",
          "speaker_id": "2",
          "time": "20210908 00:30"
        },
        {
          "id": "MDRW2100044989.1.16",
          "form": "음냠냠",
          "original_form": "음냠냠",
          "speaker_id": "1",
          "time": "20210908 00:30"
        },
        {
          "id": "MDRW2100044989.1.17",
          "form": "대학도 좋은데 다니는 것 같던데... 진짜 그게 제일 답답했음 세상물정 너무모르고...",
          "original_form": "대학도 좋은데 다니는 것 같던데... 진짜 그게 제일 답답했음 세상물정 너무모르고...",
          "speaker_id": "2",
          "time": "20210908 00:30"
        },
        {
          "id": "MDRW2100044989.1.18",
          "form": "그 늑대나 인간의 삶 하나만을 선택하라고 애들한테 그러는것두",
          "original_form": "그 늑대나 인간의 삶 하나만을 선택하라고 애들한테 그러는것두",
          "speaker_id": "1",
          "time": "20210908 00:30"
        },
        {
          "id": "MDRW2100044989.1.19",
          "form": "이해가 안갓고",
          "original_form": "이해가 안갓고",
          "speaker_id": "1",
          "time": "20210908 00:30"
        },
        {
          "id": "MDRW2100044989.1.20",
          "form": "꼭 포기해야하는 일일까용?",
          "original_form": "꼭 포기해야하는 일일까용?",
          "speaker_id": "1",
          "time": "20210908 00:31"
        },
        {
          "id": "MDRW2100044989.1.21",
          "form": "맞아.............그것 자체도 너무 폭력적으로 느껴졌달까 그 남자애야 뭐... 늑대의 삶을 더 원한것 같긴 한데",
          "original_form": "맞아.............그것 자체도 너무 폭력적으로 느껴졌달까 그 남자애야 뭐... 늑대의 삶을 더 원한것 같긴 한데",
          "speaker_id": "2",
          "time": "20210908 00:31"
        },
        {
          "id": "MDRW2100044989.1.22",
          "form": "여자애가 너무 불쌍했어....",
          "original_form": "여자애가 너무 불쌍했어....",
          "speaker_id": "2",
          "time": "20210908 00:31"
        },
        {
          "id": "MDRW2100044989.1.23",
          "form": "그리고 아들친구는 그럴바에 공부 열심히 해서 그 산 니가 매입하는게 산을 지키는데에 더 도움 되지 않을까?",
          "original_form": "그리고 아들친구는 그럴바에 공부 열심히 해서 그 산 니가 매입하는게 산을 지키는데에 더 도움 되지 않을까?",
          "speaker_id": "1",
          "time": "20210908 00:31"
        },
        {
          "id": "MDRW2100044989.1.24",
          "form": "아 완전 자본주의적 그것이야 아 ㅠㅠㅠㅠㅠㅠㅠㅠㅠㅠㅠㅠ하지만 맞는말",
          "original_form": "아 완전 자본주의적 그것이야 아 ㅠㅠㅠㅠㅠㅠㅠㅠㅠㅠㅠㅠ하지만 맞는말",
          "speaker_id": "2",
          "time": "20210908 00:31"
        },
        {
          "id": "MDRW2100044989.1.25",
          "form": "산을 지켜야해서 뒷산으로 떠난다는 어쩌구 자체가 나에게 너무 설득력이 떨어졌음",
          "original_form": "산을 지켜야해서 뒷산으로 떠난다는 어쩌구 자체가 나에게 너무 설득력이 떨어졌음",
          "speaker_id": "1",
          "time": "20210908 00:32"
        },
        {
          "id": "MDRW2100044989.1.26",
          "form": "(여기 설득력이 떨어지는 설득을 하는 사람이 있습니다)",
          "original_form": "(여기 설득력이 떨어지는 설득을 하는 사람이 있습니다)",
          "speaker_id": "1",
          "time": "20210908 00:32"
        },
        {
          "id": "MDRW2100044989.1.27",
          "form": "맞아...그냥 늑대로서 살고 싶었던 거 아냐? 솔직히 그 생각밖에 안했던 기억",
          "original_form": "맞아...그냥 늑대로서 살고 싶었던 거 아냐? 솔직히 그 생각밖에 안했던 기억",
          "speaker_id": "2",
          "time": "20210908 00:32"
        },
        {
          "id": "MDRW2100044989.1.28",
          "form": "어케...지킬건데(근본적물음)ㅋㅋㅋㅋㅋㅋㅋㅋㅋㅋㅋㅋ",
          "original_form": "어케...지킬건데(근본적물음)ㅋㅋㅋㅋㅋㅋㅋㅋㅋㅋㅋㅋ",
          "speaker_id": "2",
          "time": "20210908 00:32"
        },
        {
          "id": "MDRW2100044989.1.29",
          "form": "ㄹㅇ",
          "original_form": "ㄹㅇ",
          "speaker_id": "1",
          "time": "20210908 00:32"
        },
        {
          "id": "MDRW2100044989.1.30",
          "form": "인간들이",
          "original_form": "인간들이",
          "speaker_id": "1",
          "time": "20210908 00:32"
        },
        {
          "id": "MDRW2100044989.1.31",
          "form": "개발한다고 산 밀면",
          "original_form": "개발한다고 산 밀면",
          "speaker_id": "1",
          "time": "20210908 00:32"
        },
        {
          "id": "MDRW2100044989.1.32",
          "form": "일일이 물어죽일거냐고",
          "original_form": "일일이 물어죽일거냐고",
          "speaker_id": "1",
          "time": "20210908 00:32"
        },
        {
          "id": "MDRW2100044989.1.33",
          "form": "앙???",
          "original_form": "앙???",
          "speaker_id": "1",
          "time": "20210908 00:33"
        },
        {
          "id": "MDRW2100044989.1.34",
          "form": "다 물어죽일수 있는 이야기냐고~~",
          "original_form": "다 물어죽일수 있는 이야기냐고~~",
          "speaker_id": "1",
          "time": "20210908 00:33"
        }
      ]
    }
  ]
}
