{
  "id": "MDRW2100010900",
  "metadata": {
    "title": "국립국어원 온라인 대화 말뭉치 MDRW2100010900",
    "creator": "국립국어원",
    "distributor": "국립국어원",
    "year": "2021",
    "category": "온라인 대화 > 2인 대화",
    "annotation_level": "원시",
    "sampling": "실시간 대화"
  },
  "document": [
    {
      "id": "MDRW2100010900.1",
      "metadata": {
        "title": "온라인 대화",
        "author": "개인 대화 참여자",
        "publisher": "심심이",
        "date": "20210823",
        "topic": "미용과 건강",
        "speaker": [
          {
            "id": "1",
            "age": "20대",
            "occupation": "판매/영업 종사자",
            "sex": "여성",
            "birthplace": "서울",
            "pricipal_residence": "서울",
            "current_residence": "서울",
            "device": "스마트폰",
            "keyboard": "2벌식(쿼티)"
          },
          {
            "id": "2",
            "age": "20대",
            "occupation": "기타",
            "sex": "여성",
            "birthplace": "경기",
            "pricipal_residence": "경기",
            "current_residence": "경기",
            "device": "스마트폰",
            "keyboard": "2벌식(쿼티)"
          }
        ],
        "setting": {
          "relation": "낯선 사람",
          "intimacy": 0,
          "contact_frequency": "처음 연락한다"
        }
      },
      "utterance": [
        {
          "id": "MDRW2100010900.1.1",
          "form": "주짓수 함 해보시는고 추천해요..!",
          "original_form": "주짓수 함 해보시는고 추천해요..!",
          "speaker_id": "2",
          "time": "20210823 22:45"
        },
        {
          "id": "MDRW2100010900.1.2",
          "form": "진짜해봐야겟어요",
          "original_form": "진짜해봐야겟어요",
          "speaker_id": "1",
          "time": "20210823 22:45"
        },
        {
          "id": "MDRW2100010900.1.3",
          "form": "항상 배워보고싶어만 하고 시도는 못햇거든요",
          "original_form": "항상 배워보고싶어만 하고 시도는 못햇거든요",
          "speaker_id": "1",
          "time": "20210823 22:46"
        },
        {
          "id": "MDRW2100010900.1.4",
          "form": "그 옷이 진짜 무겁더라구요",
          "original_form": "그 옷이 진짜 무겁더라구요",
          "speaker_id": "1",
          "time": "20210823 22:46"
        },
        {
          "id": "MDRW2100010900.1.5",
          "form": "헉 마자요~ 도복이 좀 무겁긴한대",
          "original_form": "헉 마자요~ 도복이 좀 무겁긴한대",
          "speaker_id": "2",
          "time": "20210823 22:46"
        },
        {
          "id": "MDRW2100010900.1.6",
          "form": "입으면 머 딱히 무겁단생각은 안들더라구요",
          "original_form": "입으면 머 딱히 무겁단생각은 안들더라구요",
          "speaker_id": "2",
          "time": "20210823 22:46"
        },
        {
          "id": "MDRW2100010900.1.7",
          "form": "글고 주짓수 도복이 예쁜 게 많아요...",
          "original_form": "글고 주짓수 도복이 예쁜 게 많아요...",
          "speaker_id": "2",
          "time": "20210823 22:46"
        },
        {
          "id": "MDRW2100010900.1.8",
          "form": "아그게",
          "original_form": "아그게",
          "speaker_id": "1",
          "time": "20210823 22:47"
        },
        {
          "id": "MDRW2100010900.1.9",
          "form": "흰색 파란색만 입는건 또 아니군요",
          "original_form": "흰색 파란색만 입는건 또 아니군요",
          "speaker_id": "1",
          "time": "20210823 22:47"
        },
        {
          "id": "MDRW2100010900.1.10",
          "form": "네 근데 아마 도장마다 다를거예요 주짓수에도 파벌 비슷한 게 있는데 그 파벌에 소속된 도장은 색깔 있는 도복은 못입게하는 곳도 있다고 들었어요",
          "original_form": "네 근데 아마 도장마다 다를거예요 주짓수에도 파벌 비슷한 게 있는데 그 파벌에 소속된 도장은 색깔 있는 도복은 못입게하는 곳도 있다고 들었어요",
          "speaker_id": "2",
          "time": "20210823 22:51"
        },
        {
          "id": "MDRW2100010900.1.11",
          "form": "하지만 안 그런 곳도 많다는 거~~",
          "original_form": "하지만 안 그런 곳도 많다는 거~~",
          "speaker_id": "2",
          "time": "20210823 22:51"
        },
        {
          "id": "MDRW2100010900.1.12",
          "form": "저는 갠적으로 검은색이랑 파란색 도복 좋아했어ㅛ어욤",
          "original_form": "저는 갠적으로 검은색이랑 파란색 도복 좋아했어ㅛ어욤",
          "speaker_id": "2",
          "time": "20210823 22:52"
        },
        {
          "id": "MDRW2100010900.1.13",
          "form": "헐ㅋㅋㅋㅋㅋㅋㅋ그건 진짜 신기한 사실이네욬ㅋㅋㅋㅋㅋ",
          "original_form": "헐ㅋㅋㅋㅋㅋㅋㅋ그건 진짜 신기한 사실이네욬ㅋㅋㅋㅋㅋ",
          "speaker_id": "1",
          "time": "20210823 22:52"
        },
        {
          "id": "MDRW2100010900.1.14",
          "form": "파벌이 있구나",
          "original_form": "파벌이 있구나",
          "speaker_id": "1",
          "time": "20210823 22:52"
        },
        {
          "id": "MDRW2100010900.1.15",
          "form": "검은색 도복에 흰색 벨트 너무 멋질거같아요",
          "original_form": "검은색 도복에 흰색 벨트 너무 멋질거같아요",
          "speaker_id": "1",
          "time": "20210823 22:52"
        },
        {
          "id": "MDRW2100010900.1.16",
          "form": "도장에 들어가는 것도 신중히 들어가야겟네요",
          "original_form": "도장에 들어가는 것도 신중히 들어가야겟네요",
          "speaker_id": "1",
          "time": "20210823 22:52"
        },
        {
          "id": "MDRW2100010900.1.17",
          "form": "마자요 !! 잘 알아보는거 중요해요!!",
          "original_form": "마자요 !! 잘 알아보는거 중요해요!!",
          "speaker_id": "2",
          "time": "20210823 22:53"
        },
        {
          "id": "MDRW2100010900.1.18",
          "form": "완전 좋은 정보 많이 얻엇습니다 name2님 덕분에",
          "original_form": "완전 좋은 정보 많이 얻엇습니다 &name2&님 덕분에",
          "speaker_id": "1",
          "time": "20210823 22:54"
        },
        {
          "id": "MDRW2100010900.1.19",
          "form": "으헤헤",
          "original_form": "으헤헤",
          "speaker_id": "2",
          "time": "20210823 22:54"
        },
        {
          "id": "MDRW2100010900.1.20",
          "form": "다른 운동 배워보고싶은신 것도 잇으세요,?",
          "original_form": "다른 운동 배워보고싶은신 것도 잇으세요,?",
          "speaker_id": "1",
          "time": "20210823 22:54"
        },
        {
          "id": "MDRW2100010900.1.21",
          "form": "저는 앞으로 한 1년은 격한 운동은 못 할거같아서",
          "original_form": "저는 앞으로 한 1년은 격한 운동은 못 할거같아서",
          "speaker_id": "2",
          "time": "20210823 22:55"
        },
        {
          "id": "MDRW2100010900.1.22",
          "form": "발레나 요가나 필라테스?? 배워보고싶어요",
          "original_form": "발레나 요가나 필라테스?? 배워보고싶어요",
          "speaker_id": "2",
          "time": "20210823 22:55"
        },
        {
          "id": "MDRW2100010900.1.23",
          "form": "헉 그러시군요 ㅜㅜㅜ뭐든 다 잘하실 것같아요 주짓수 하실 정도면 ㅋㅋㅋㅋ",
          "original_form": "헉 그러시군요 ㅜㅜㅜ뭐든 다 잘하실 것같아요 주짓수 하실 정도면 ㅋㅋㅋㅋ",
          "speaker_id": "1",
          "time": "20210823 22:56"
        },
        {
          "id": "MDRW2100010900.1.24",
          "form": "ㅋㅋㅋㅋㅋㅋㅋ아 ㅎㅎ 감사합니다 name1님도 잘하실거예요!!",
          "original_form": "ㅋㅋㅋㅋㅋㅋㅋ아 ㅎㅎ 감사합니다 &name1&님도 잘하실거예요!!",
          "speaker_id": "2",
          "time": "20210823 22:56"
        }
      ]
    }
  ]
}
