{
  "id": "MDRW2100046142",
  "metadata": {
    "title": "국립국어원 온라인 대화 말뭉치 MDRW2100046142",
    "creator": "국립국어원",
    "distributor": "국립국어원",
    "year": "2021",
    "category": "온라인 대화 > 2인 대화",
    "annotation_level": "원시",
    "sampling": "실시간 대화"
  },
  "document": [
    {
      "id": "MDRW2100046142.1",
      "metadata": {
        "title": "온라인 대화",
        "author": "개인 대화 참여자",
        "publisher": "심심이",
        "date": "20210908",
        "topic": "일과 직업",
        "speaker": [
          {
            "id": "1",
            "age": "20대",
            "occupation": "무직/취업 준비생",
            "sex": "여성",
            "birthplace": "제주",
            "pricipal_residence": "충북",
            "current_residence": "충북",
            "device": "스마트폰",
            "keyboard": "2벌식(쿼티)"
          },
          {
            "id": "2",
            "age": "30대",
            "occupation": "전문가 및 관련 종사자",
            "sex": "여성",
            "birthplace": "부산",
            "pricipal_residence": "부산",
            "current_residence": "대구",
            "device": "스마트폰",
            "keyboard": "천지인"
          }
        ],
        "setting": {
          "relation": "낯선 사람",
          "intimacy": 0,
          "contact_frequency": "처음 연락한다"
        }
      },
      "utterance": [
        {
          "id": "MDRW2100046142.1.1",
          "form": "안녕하세요",
          "original_form": "안녕하세요",
          "speaker_id": "1",
          "time": "20210908 10:41"
        },
        {
          "id": "MDRW2100046142.1.2",
          "form": "네네",
          "original_form": "네네",
          "speaker_id": "2",
          "time": "20210908 10:41"
        },
        {
          "id": "MDRW2100046142.1.3",
          "form": "업무 스트레스 많으세요?",
          "original_form": "업무 스트레스 많으세요?",
          "speaker_id": "1",
          "time": "20210908 10:42"
        },
        {
          "id": "MDRW2100046142.1.4",
          "form": "없어용",
          "original_form": "없어용",
          "speaker_id": "2",
          "time": "20210908 10:42"
        },
        {
          "id": "MDRW2100046142.1.5",
          "form": "근무환경이좋은편이라서ㅎㅎ",
          "original_form": "근무환경이좋은편이라서ㅎㅎ",
          "speaker_id": "2",
          "time": "20210908 10:42"
        },
        {
          "id": "MDRW2100046142.1.6",
          "form": "옹 좋네용",
          "original_form": "옹 좋네용",
          "speaker_id": "1",
          "time": "20210908 10:43"
        },
        {
          "id": "MDRW2100046142.1.7",
          "form": "잇으신가여ㅜ?",
          "original_form": "잇으신가여ㅜ?",
          "speaker_id": "2",
          "time": "20210908 10:43"
        },
        {
          "id": "MDRW2100046142.1.8",
          "form": "저는 정직원이 아니라서ㅜㅜ 스펙 쌓는게 좀 스트레스 같아요",
          "original_form": "저는 정직원이 아니라서ㅜㅜ 스펙 쌓는게 좀 스트레스 같아요",
          "speaker_id": "1",
          "time": "20210908 10:45"
        },
        {
          "id": "MDRW2100046142.1.9",
          "form": "에궁ㅜㅜ",
          "original_form": "에궁ㅜㅜ",
          "speaker_id": "2",
          "time": "20210908 10:45"
        },
        {
          "id": "MDRW2100046142.1.10",
          "form": "그럴수잇져ㅜㅜ",
          "original_form": "그럴수잇져ㅜㅜ",
          "speaker_id": "2",
          "time": "20210908 10:45"
        },
        {
          "id": "MDRW2100046142.1.11",
          "form": "그래서 이것저것 시험 보러 다니는데 ㅇㅅㅠ",
          "original_form": "그래서 이것저것 시험 보러 다니는데 ㅇㅅㅠ",
          "speaker_id": "1",
          "time": "20210908 10:46"
        },
        {
          "id": "MDRW2100046142.1.12",
          "form": "이 생활 그만 하고 싶어요ㅠㅠ",
          "original_form": "이 생활 그만 하고 싶어요ㅠㅠ",
          "speaker_id": "1",
          "time": "20210908 10:46"
        },
        {
          "id": "MDRW2100046142.1.13",
          "form": "ㅜㅜ 힘내세여",
          "original_form": "ㅜㅜ 힘내세여",
          "speaker_id": "2",
          "time": "20210908 10:46"
        },
        {
          "id": "MDRW2100046142.1.14",
          "form": "저두",
          "original_form": "저두",
          "speaker_id": "2",
          "time": "20210908 10:46"
        },
        {
          "id": "MDRW2100046142.1.15",
          "form": "그랫어서",
          "original_form": "그랫어서",
          "speaker_id": "2",
          "time": "20210908 10:46"
        },
        {
          "id": "MDRW2100046142.1.16",
          "form": "충분히 이해해요ㅜㅜㅜㅜ",
          "original_form": "충분히 이해해요ㅜㅜㅜㅜ",
          "speaker_id": "2",
          "time": "20210908 10:46"
        },
        {
          "id": "MDRW2100046142.1.17",
          "form": "최근에는 jlpt시험 접수했네요ㅠㅜ",
          "original_form": "최근에는 jlpt시험 접수했네요ㅠㅜ",
          "speaker_id": "1",
          "time": "20210908 10:47"
        },
        {
          "id": "MDRW2100046142.1.18",
          "form": "우와",
          "original_form": "우와",
          "speaker_id": "2",
          "time": "20210908 10:47"
        },
        {
          "id": "MDRW2100046142.1.19",
          "form": "일어잘하시나여!!!!",
          "original_form": "일어잘하시나여!!!!",
          "speaker_id": "2",
          "time": "20210908 10:47"
        },
        {
          "id": "MDRW2100046142.1.20",
          "form": "그냥 고등학교 때 제이외국어 선택한 정도에요",
          "original_form": "그냥 고등학교 때 제이외국어 선택한 정도에요",
          "speaker_id": "1",
          "time": "20210908 10:49"
        },
        {
          "id": "MDRW2100046142.1.21",
          "form": "오오 멋잇어요ㅜㅜ",
          "original_form": "오오 멋잇어요ㅜㅜ",
          "speaker_id": "2",
          "time": "20210908 10:50"
        }
      ]
    }
  ]
}
